snake/__init__.py
snake/__main__.py
snake/food.py
snake/snake.py
snake/snake_main.py
icenter_snake-0.3.0.dist-info/LICENSE
icenter_snake-0.3.0.dist-info/METADATA
icenter_snake-0.3.0.dist-info/WHEEL
icenter_snake-0.3.0.dist-info/top_level.txt
icenter_snake-0.3.0.dist-info/RECORD
