Metadata-Version: 2.1
Name: icenter-snake
Version: 0.3.0
Summary: Pygame implementation of the snake video game
Home-page: https://pypi.org/project/icenter_snake
Author: James Kabbes
Author-email: james.kabbes@gmail.com
Project-URL: GitHub, https://github.com/AmerenICenter/snake
Project-URL: Documentation, https://amerenicenter.github.io/snake/
Classifier: Programming Language :: Python :: 3
Classifier: License :: OSI Approved :: MIT License
Classifier: Operating System :: OS Independent
Requires-Python: >=3.7
License-File: LICENSE
Requires-Dist: pygame
